{
  "billiardBallButton.png": {
    "text": [
      "Copyright 2002-2019 University of Colorado Boulder"
    ],
    "projectURL": "https://phet.colorado.edu",
    "license": "contact phethelp@colorado.edu",
    "notes": "created by Amy Hanson"
  },
  "bohrButton.png": {
    "text": [
      "Copyright 2002-2019 University of Colorado Boulder"
    ],
    "projectURL": "https://phet.colorado.edu",
    "license": "contact phethelp@colorado.edu",
    "notes": "created by Amy Hanson"
  },
  "classicalSolarSystemButton.png": {
    "text": [
      "Copyright 2002-2019 University of Colorado Boulder"
    ],
    "projectURL": "https://phet.colorado.edu",
    "license": "contact phethelp@colorado.edu",
    "notes": "created by Amy Hanson"
  },
  "deBroglieButton.png": {
    "text": [
      "Copyright 2002-2019 University of Colorado Boulder"
    ],
    "projectURL": "https://phet.colorado.edu",
    "license": "contact phethelp@colorado.edu",
    "notes": "created by Amy Hanson"
  },
  "energyLevelsScreenIcon.png": {
    "text": [
      "Copyright 2022 University of Colorado Boulder"
    ],
    "projectURL": "https://phet.colorado.edu",
    "license": "contact phethelp@colorado.edu",
    "notes": "created by Amy Hanson"
  },
  "kaboom.png": {
    "text": [
      "Copyright 2002-2015 University of Colorado Boulder"
    ],
    "projectURL": "https://phet.colorado.edu",
    "license": "contact phethelp@colorado.edu",
    "notes": "ported from Java version"
  },
  "plumPudding.png": {
    "text": [
      "Copyright 2002-2015 University of Colorado Boulder"
    ],
    "projectURL": "https://phet.colorado.edu",
    "license": "contact phethelp@colorado.edu",
    "notes": "ported from Java version"
  },
  "plumPuddingButton.png": {
    "text": [
      "Copyright 2002-2019 University of Colorado Boulder"
    ],
    "projectURL": "https://phet.colorado.edu",
    "license": "contact phethelp@colorado.edu",
    "notes": "created by Amy Hanson"
  },
  "schrodingerButton.png": {
    "text": [
      "Copyright 2002-2019 University of Colorado Boulder"
    ],
    "projectURL": "https://phet.colorado.edu",
    "license": "contact phethelp@colorado.edu",
    "notes": "created by Amy Hanson"
  },
  "spectraScreenIcon.png": {
    "text": [
      "Copyright 2022 University of Colorado Boulder"
    ],
    "projectURL": "https://phet.colorado.edu",
    "license": "contact phethelp@colorado.edu",
    "notes": "created by Amy Hanson"
  }
}